{"id": 708, "name": "Squid Costume Summer", "status": "Dead", "species": "Robot", "type": "Decoy", "gender": "Female", "origin": {"name": "Earth (Replacement Dimension)", "url": "https://rickandmortyapi.com/api/location/20"}, "location": {"name": "Earth (Replacement Dimension)", "url": "https://rickandmortyapi.com/api/location/20"}, "image": "https://rickandmortyapi.com/api/character/avatar/708.jpeg", "episode": ["https://rickandmortyapi.com/api/episode/43"], "url": "https://rickandmortyapi.com/api/character/708", "created": "2021-10-16T16:03:02.153Z"}