{"id": 742, "name": "Bruce Chutback", "status": "Alive", "species": "Human", "type": "", "gender": "Male", "origin": {"name": "Earth (Replacement Dimension)", "url": "https://rickandmortyapi.com/api/location/20"}, "location": {"name": "Earth (Replacement Dimension)", "url": "https://rickandmortyapi.com/api/location/20"}, "image": "https://rickandmortyapi.com/api/character/avatar/742.jpeg", "episode": ["https://rickandmortyapi.com/api/episode/46"], "url": "https://rickandmortyapi.com/api/character/742", "created": "2021-10-17T13:35:30.793Z"}